bibtextools/__init__.py
bibtextools/__main__.py
bibtextools/clean_bib_file.py
bibtextools/cli.py
bibtextools/combine_bib_files.py
bibtextools/const.py
bibtextools/modernize_bib_file.py
bibtextools/util.py
bibtextools-0.5.0.dist-info/LICENSE
bibtextools-0.5.0.dist-info/METADATA
bibtextools-0.5.0.dist-info/WHEEL
bibtextools-0.5.0.dist-info/entry_points.txt
bibtextools-0.5.0.dist-info/top_level.txt
bibtextools-0.5.0.dist-info/RECORD
