Metadata-Version: 2.1
Name: bibtextools
Version: 0.5.0
Summary: Tools for working with BibTeX files
Author-email: Karl-Ludwig Besser <karl.besser@princeton.edu>
License: GNU GENERAL PUBLIC LICENSE
Project-URL: Repository, https://github.com/klb2/bibtex-tools.git
Project-URL: Changelog, https://github.com/klb2/bibtex-tools/blob/master/CHANGELOG.md
Keywords: bibtex,latex,biber,bibliography
Classifier: Intended Audience :: Science/Research
Classifier: License :: OSI Approved :: GNU General Public License v3 (GPLv3)
Classifier: Programming Language :: Python :: 3
Classifier: Programming Language :: Python :: 3 :: Only
Classifier: Topic :: Scientific/Engineering
Requires-Python: >=3.8
License-File: LICENSE
Requires-Dist: bibtexparser <2
Requires-Dist: feedparser
Requires-Dist: click
Requires-Dist: pyiso4 >=0.1.3
Provides-Extra: test
Requires-Dist: pytest ; extra == 'test'
